packageTest/__init__.py
packageTest/packageTest.py
packageTest/packageTest_test.py
torch_recommenders/__init__.py
torch_recommenders/torch_recommenders_test.py
torch_recommenders/datasets/__init__.py
torch_recommenders/datasets/datasets_test.py
torch_recommenders/datasets/movielens.py
torch_recommenders/datasets/test_datasets.py
torch_recommenders/examples/__init__.py
torch_recommenders/examples/evaluation.py
torch_recommenders/examples/main.py
torch_recommenders/examples/test.py
torch_recommenders/examples/utils.py
torch_recommenders/models/DeepFM.py
torch_recommenders/models/FM.py
torch_recommenders/models/NCF.py
torch_recommenders/models/NFM.py
torch_recommenders/models/Wide_Deep.py
torch_recommenders/models/__init__.py
torch_recommenders/models/layer.py
torch_recommenders/models/xDeepFM.py
torch_recommenders/utils/EarlyStopper.py
torch_recommenders/utils/__init__.py
torch_recommenders/utils/evaluation.py
torch_recommenders-0.0.7.dist-info/LICENSE
torch_recommenders-0.0.7.dist-info/METADATA
torch_recommenders-0.0.7.dist-info/WHEEL
torch_recommenders-0.0.7.dist-info/top_level.txt
torch_recommenders-0.0.7.dist-info/RECORD
