Metadata-Version: 2.1
Name: torch-recommenders
Version: 0.0.7
Summary: Recommendation System for Pytorch
Home-page: https://github.com/HardenKim/torch-recommenders
Author: HardenKim
Author-email: tazzang0921@gmail.com
License: UNKNOWN
Keywords: RecSys,Pytorch
Platform: UNKNOWN
Classifier: Programming Language :: Python :: 3
Classifier: License :: OSI Approved :: MIT License
Classifier: Operating System :: OS Independent
Requires-Python: >=3
License-File: LICENSE
Requires-Dist: torch (>=1.10)
Requires-Dist: tensorboardX (>=2.5)
Requires-Dist: numpy (>=1.21)
Requires-Dist: pandas (>=1.3scipy>=1.5tqdm>=4.62)
Requires-Dist: argparse (>=1.1)
